{
    "art": [
        "babyfaces.png",
        "BerkeleyMarina.jpg",
        "china.lily.pond2.png",
        "china.town.parking2.jpg",
        "DemonDude.jpg",
        "erikly1.jpg",
        "garfield.ave.trees.jpg",
        "Giannis.jpg",
        "Gus.jpg",
        "Jawas.jpg",
        "Kawhi.jpg",
        "koi.jpg",
        "mrmattzan1.jpg",
        "OaklandBay.jpg",
        "SantaMonicaBrocolliTrees.jpg",
        "Sheriff.jpg",
        "thiago1.jpg",
        "Titan.jpg",
        "well.worth.lot2.png",
        "WestwoodIntersection.jpg"
    ],
    "learning": [
        "fantasy_scoring.png",
        "my_team.png",
        "NASHboard1.png",
        "player_display.png",
        "player_faceted_search.png",
        "python_web_scraping_ultimate_guide.png",
        "yt_tut.png"
    ],
    "data": [
        "fantano1.png",
        "fantano2.png",
        "Geocheloneplatynota.jpg",
        "Gopherusagassizii.jpg",
        "IND-logo.png",
        "Kinixyserosa.jpg",
        "LAL-logo.png",
        "nba1.png",
        "nyt_mini_scores3.png",
        "POR-logo.png",
        "Testudohorsfieldii.jpg",
        "tort1.png",
        "tortoise_taxonomy1.png"
    ],
    "people": [
        "blokes (1).jpg",
        "blokes (2).jpg",
        "blokes (3).jpg",
        "hoop.jpg",
        "me (1).jpg",
        "me (2).jpg",
        "me.jpg",
        "me.png",
        "me2.png",
        "me3.jpg",
        "me3.png",
        "pigpencil.png",
        "sirs.jpg",
        "son1.jpg",
        "son2.jpg",
        "son3.jpg"
    ],
    "writing": [
        "beef.png",
        "beef_everywhere_all_at_once.png",
        "berk_nature1.png",
        "berk_nature2.png",
        "eye.png",
        "leaf.png",
        "self_esteem.png",
        "self_esteem1.png",
        "self_esteem2.png",
        "writing (2).png",
        "writing.png"
    ]
}